<markers>
<marker lat="-14.8333333333333" lng="-164.866666666667" src="" date="2002-07-08 05:31:00" coords="014d 50.00 S / 164d 52.00 W" comment=""/>
<marker lat="-13.8333333333333" lng="-171.133333333333" src="" date="2002-07-11 05:40:00" coords="013d 50.00 S / 171d 08.00 W" comment=""/>
<marker lat="6.3" lng="99.85" src="" date="2003-06-19 15:21:00" coords="006d 18.00 N / 099d 51.00 E" comment=""/>
<marker lat="6.3" lng="99.85" src="" date="2003-06-22 16:35:00" coords="006d 18.00 N / 099d 51.00 E" comment=""/>
<marker lat="6.3" lng="99.85" src="" date="2003-07-08 16:36:00" coords="006d 18.00 N / 099d 51.00 E" comment=""/>
<marker lat="6.3" lng="99.85" src="" date="2003-07-14 15:56:00" coords="006d 18.00 N / 099d 51.00 E" comment=""/>
<marker lat="6.3" lng="99.85" src="" date="2003-07-15 11:29:00" coords="006d 18.00 N / 099d 51.00 E" comment=""/>
<marker lat="6.3" lng="99.85" src="" date="2003-07-31 18:10:00" coords="006d 18.00 N / 099d 51.00 E" comment=""/>
<marker lat="6.3" lng="99.85" src="" date="2003-08-02 04:24:00" coords="006d 18.00 N / 099d 51.00 E" comment=""/>
<marker lat="6.3" lng="99.85" src="" date="2003-08-03 16:31:00" coords="006d 18.00 N / 099d 51.00 E" comment=""/>
<marker lat="6.3" lng="99.85" src="" date="2003-08-06 17:30:00" coords="006d 18.00 N / 099d 51.00 E" comment=""/>
<marker lat="6.3" lng="99.85" src="" date="2003-08-14 04:17:00" coords="006d 18.00 N / 099d 51.00 E" comment=""/>
<marker lat="6.3" lng="99.85" src="" date="2003-08-22 14:55:00" coords="006d 18.00 N / 099d 51.00 E" comment=""/>
<marker lat="6.3" lng="99.85" src="" date="2003-08-26 03:58:00" coords="006d 18.00 N / 099d 51.00 E" comment=""/>
<marker lat="7.63333333333333" lng="99.9833333333333" src="" date="2003-09-08 16:16:00" coords="007d 38.00 N / 099d 59.00 E" comment=""/>
<marker lat="6.3" lng="99.85" src="" date="2003-09-30 14:13:00" coords="006d 18.00 N / 099d 51.00 E" comment=""/>
<marker lat="6.3" lng="99.85" src="" date="2003-11-05 14:42:00" coords="006d 18.00 N / 099d 51.00 E" comment=""/>
<marker lat="6.3" lng="99.85" src="" date="2003-11-08 11:18:00" coords="006d 18.00 N / 099d 51.00 E" comment=""/>
</markers>