<markers>
<marker lat="17.8333333333333" lng="-66.6" src="" date="2002-03-21 15:59:00" coords="017d 50.00 N / 066d 36.00 W" comment=""/>
<marker lat="17.65" lng="-68.5666666666667" src="" date="2002-03-22 16:01:00" coords="017d 39.00 N / 068d 34.00 W" comment=""/>
<marker lat="17.55" lng="-70.3166666666667" src="" date="2002-03-23 16:00:00" coords="017d 33.00 N / 070d 19.00 W" comment=""/>
<marker lat="17.5" lng="-72.3333333333333" src="" date="2002-03-24 14:46:00" coords="017d 30.00 N / 072d 20.00 W" comment=""/>
<marker lat="17.9333333333333" lng="-74.5833333333333" src="" date="2002-03-25 15:43:00" coords="017d 56.00 N / 074d 35.00 W" comment=""/>
<marker lat="18.9" lng="-78.6" src="" date="2002-04-06 19:06:00" coords="018d 54.00 N / 078d 36.00 W" comment=""/>
<marker lat="21.4833333333333" lng="-83.2166666666667" src="" date="2002-04-21 19:59:00" coords="021d 29.00 N / 083d 13.00 W" comment=""/>
<marker lat="23.1666666666667" lng="-84.7" src="" date="2002-04-25 14:21:00" coords="023d 10.00 N / 084d 42.00 W" comment=""/>
<marker lat="30.9666666666667" lng="-65.8166666666667" src="" date="2002-11-14 11:48:00" coords="030d 58.00 N / 065d 49.00 W" comment=""/>
<marker lat="29.0833333333333" lng="-65.55" src="" date="2002-11-15 12:07:00" coords="029d 05.00 N / 065d 33.00 W" comment=""/>
<marker lat="27.0333333333333" lng="-65.0833333333333" src="" date="2002-11-16 11:44:00" coords="027d 02.00 N / 065d 05.00 W" comment=""/>
<marker lat="25.1333333333333" lng="-65.2" src="" date="2002-11-17 11:53:00" coords="025d 08.00 N / 065d 12.00 W" comment=""/>
<marker lat="23.0833333333333" lng="-65.0166666666667" src="" date="2002-11-18 11:58:00" coords="023d 05.00 N / 065d 01.00 W" comment=""/>
<marker lat="21.2833333333333" lng="-64.6666666666667" src="" date="2002-11-19 11:44:00" coords="021d 17.00 N / 064d 40.00 W" comment=""/>
<marker lat="12.2166666666667" lng="-61.1333333333333" src="" date="2003-03-26 13:19:00" coords="012d 13.00 N / 061d 08.00 W" comment=""/>
<marker lat="16.0016666666667" lng="-87.0098333333333" src="WINLINK" date="2005-07-13 19:25:00" coords="016d 00.00 N / 087d 00.00 W" comment="On Passage to Rio Dulce Guatemala"/>
<marker lat="15.9795" lng="-88.5461666666667" src="WINLINK" date="2005-07-14 14:15:00" coords="015d 58.00 N / 088d 32.00 W" comment="Approaching the  Rio Dulce Guatemala"/>
<marker lat="15.779" lng="-88.8026666666667" src="WINLINK" date="2005-07-14 23:10:00" coords="015d 46.00 N / 088d 48.00 W" comment="Rio Dulce Guatemala"/>
<marker lat="15.666" lng="-88.9916666666667" src="WINLINK" date="2005-07-16 22:22:00" coords="015d 39.00 N / 088d 59.00 W" comment="Monkey Bay Marina, Fronteras, Rio Dulce Guatemala"/>
<marker lat="15.666" lng="-88.9916666666667" src="WINLINK" date="2005-08-10 22:42:00" coords="015d 39.00 N / 088d 59.00 W" comment="Returned  back in Monkey Bay Marina, Fronteras, Rio Dulce Guatemala"/>
</markers>