<markers>
<marker lat="12.1666666666667" lng="-87.0833333333333" src="" date="2003-06-21 22:23:00" coords="012d 10.00 N / 087d 05.00 W" comment=""/>
<marker lat="10.9166666666667" lng="-85.7833333333333" src="" date="2003-06-23 00:51:00" coords="010d 55.00 N / 085d 47.00 W" comment=""/>
<marker lat="10.9333333333333" lng="-85.9333333333333" src="" date="2003-06-27 15:30:00" coords="010d 56.00 N / 085d 56.00 W" comment=""/>
<marker lat="10.8666666666667" lng="-85.9" src="" date="2003-06-28 14:52:00" coords="010d 52.00 N / 085d 54.00 W" comment=""/>
<marker lat="10.5833333333333" lng="-85.65" src="" date="2003-07-02 23:28:00" coords="010d 35.00 N / 085d 39.00 W" comment=""/>
<marker lat="9.75" lng="-84.9833333333333" src="" date="2003-07-17 09:12:00" coords="009d 45.00 N / 084d 59.00 W" comment=""/>
<marker lat="9.65" lng="-84.6666666666667" src="" date="2003-07-20 17:50:00" coords="009d 39.00 N / 084d 40.00 W" comment=""/>
<marker lat="9.93333333333333" lng="-84.9666666666667" src="" date="2003-07-23 19:40:00" coords="009d 56.00 N / 084d 58.00 W" comment=""/>
<marker lat="9.98333333333333" lng="-84.8" src="" date="2003-07-29 20:41:00" coords="009d 59.00 N / 084d 48.00 W" comment=""/>
<marker lat="9.48333333333333" lng="-84.55" src="" date="2003-08-13 17:19:00" coords="009d 29.00 N / 084d 33.00 W" comment=""/>
<marker lat="8.7" lng="-83.6666666666667" src="" date="2003-08-14 21:29:00" coords="008d 42.00 N / 083d 40.00 W" comment=""/>
<marker lat="8.61666666666667" lng="-83.15" src="" date="2003-08-17 00:50:00" coords="008d 37.00 N / 083d 09.00 W" comment=""/>
<marker lat="8.13333333333333" lng="-82.3166666666667" src="" date="2003-08-24 02:11:00" coords="008d 08.00 N / 082d 19.00 W" comment=""/>
<marker lat="7.76666666666667" lng="-81.5333333333333" src="" date="2003-08-25 21:15:00" coords="007d 46.00 N / 081d 32.00 W" comment=""/>
<marker lat="7.26666666666667" lng="-80.9333333333333" src="" date="2003-08-28 22:28:00" coords="007d 16.00 N / 080d 56.00 W" comment=""/>
<marker lat="8.4" lng="-79.0833333333333" src="" date="2003-08-30 22:31:00" coords="008d 24.00 N / 079d 05.00 W" comment=""/>
<marker lat="8.51666666666667" lng="-79.0333333333333" src="" date="2003-09-01 22:12:00" coords="008d 31.00 N / 079d 02.00 W" comment=""/>
<marker lat="8.63333333333333" lng="-79.0333333333333" src="" date="2003-09-02 17:25:00" coords="008d 38.00 N / 079d 02.00 W" comment=""/>
<marker lat="8.43333333333333" lng="-78.85" src="" date="2003-09-04 21:55:00" coords="008d 26.00 N / 078d 51.00 W" comment=""/>
<marker lat="8.93333333333333" lng="-79.55" src="" date="2003-09-11 01:52:00" coords="008d 56.00 N / 079d 33.00 W" comment=""/>
<marker lat="9.35" lng="-79.9" src="" date="2003-10-08 22:16:00" coords="009d 21.00 N / 079d 54.00 W" comment=""/>
<marker lat="9.56666666666667" lng="-79.6666666666667" src="" date="2003-10-13 19:40:00" coords="009d 34.00 N / 079d 40.00 W" comment=""/>
<marker lat="9.61666666666667" lng="-79.5833333333333" src="" date="2003-10-16 16:01:00" coords="009d 37.00 N / 079d 35.00 W" comment=""/>
<marker lat="9.58333333333333" lng="-78.6666666666667" src="" date="2003-10-18 22:00:00" coords="009d 35.00 N / 078d 40.00 W" comment=""/>
<marker lat="9.93333333333333" lng="-77.1833333333333" src="" date="2003-10-28 14:48:00" coords="009d 56.00 N / 077d 11.00 W" comment=""/>
<marker lat="10.4166666666667" lng="-75.5333333333333" src="" date="2003-10-29 13:49:00" coords="010d 25.00 N / 075d 32.00 W" comment=""/>
<marker lat="11.95" lng="-76.0166666666667" src="" date="2003-11-18 13:51:00" coords="011d 57.00 N / 076d 01.00 W" comment=""/>
<marker lat="13.9333333333333" lng="-75.8833333333333" src="" date="2003-11-19 14:41:00" coords="013d 56.00 N / 075d 53.00 W" comment=""/>
<marker lat="15.45" lng="-75.3833333333333" src="" date="2003-11-20 14:45:00" coords="015d 27.00 N / 075d 23.00 W" comment=""/>
<marker lat="16.6333333333333" lng="-73.9833333333333" src="" date="2003-11-21 23:24:00" coords="016d 38.00 N / 073d 59.00 W" comment=""/>
<marker lat="17.4666666666667" lng="-73.9333333333333" src="" date="2003-11-22 12:26:00" coords="017d 28.00 N / 073d 56.00 W" comment=""/>
<marker lat="18.0333333333333" lng="-73.25" src="" date="2003-11-23 23:27:00" coords="018d 02.00 N / 073d 15.00 W" comment=""/>
<marker lat="17.6833333333333" lng="-72.2666666666667" src="" date="2003-11-24 12:27:00" coords="017d 41.00 N / 072d 16.00 W" comment=""/>
<marker lat="17.5666666666667" lng="-70.9666666666667" src="" date="2003-11-25 14:08:00" coords="017d 34.00 N / 070d 58.00 W" comment=""/>
<marker lat="18.45" lng="-69.6166666666667" src="" date="2003-11-26 18:17:00" coords="018d 27.00 N / 069d 37.00 W" comment=""/>
<marker lat="18.0166666666667" lng="-68.7666666666667" src="" date="2003-11-30 01:33:00" coords="018d 01.00 N / 068d 46.00 W" comment=""/>
<marker lat="17.95" lng="-66.8666666666667" src="" date="2003-12-02 16:03:00" coords="017d 57.00 N / 066d 52.00 W" comment=""/>
<marker lat="17.9666666666667" lng="-66.6166666666667" src="" date="2003-12-03 15:37:00" coords="017d 58.00 N / 066d 37.00 W" comment=""/>
<marker lat="18.1166666666667" lng="-65.5833333333333" src="" date="2004-02-14 13:44:00" coords="018d 07.00 N / 065d 35.00 W" comment=""/>
<marker lat="34.7256666666667" lng="-76.6653333333333" src="WINLINK" date="2005-07-22 01:17:00" coords="034d 43.00 N / 076d 39.00 W" comment="Boadicea tied up at Town Creek Marina, Beaufort, NC  Mile Marker 202"/>
<marker lat="34.9686666666667" lng="-76.5793333333333" src="WINLINK" date="2005-08-01 20:23:00" coords="034d 58.00 N / 076d 34.00 W" comment="Boadicea anchored in South River, NC.  Mile Marker 178."/>
<marker lat="35.5618333333333" lng="-76.4766666666667" src="WINLINK" date="2005-08-02 20:37:00" coords="035d 33.00 N / 076d 28.00 W" comment="Boadicea anchored in Pungo River, NC  Mile Marker 127.5."/>
<marker lat="36.2423333333333" lng="-75.9373333333333" src="WINLINK" date="2005-08-03 22:03:00" coords="036d 14.00 N / 075d 56.00 W" comment="Boadicea anchored South of Buck Island, North River, VA  Mile Marker 59."/>
<marker lat="36.352" lng="-75.9473333333333" src="WINLINK" date="2005-08-04 16:45:00" coords="036d 21.00 N / 075d 56.00 W" comment="Boadicea tied up Midway Marina, Coinjock, NC.  Mile Marker 49."/>
<marker lat="36.7211666666667" lng="-76.2411666666667" src="WINLINK" date="2005-08-07 20:29:00" coords="036d 43.00 N / 076d 14.00 W" comment="Boadicea tied up between Great Bridge and Great Bridge Lock, VA Mile Marker 11.3"/>
<marker lat="37.0173333333333" lng="-76.3418333333333" src="WINLINK" date="2005-08-08 18:12:00" coords="037d 01.00 N / 076d 20.00 W" comment="Boadicea tied up Blue Water Marina, Hampton Roads, VA"/>
<marker lat="36.8413333333333" lng="-76.2988333333333" src="WINLINK" date="2005-08-10 16:44:00" coords="036d 50.00 N / 076d 17.00 W" comment="Boadicea tied up Tide Water Marina, Portsmouth, VA"/>
<marker lat="37.318" lng="-76.4658333333333" src="WINLINK" date="2005-08-18 19:41:00" coords="037d 19.00 N / 076d 27.00 W" comment="Boadicea anchored NW Severn River, Mobjack Bay, VA"/>
<marker lat="37.6706666666667" lng="-76.33" src="WINLINK" date="2005-08-19 19:30:00" coords="037d 40.00 N / 076d 19.00 W" comment="Boadicea anchored off Grog Island, Fleets Bay, VA"/>
<marker lat="37.791" lng="-76.3295" src="WINLINK" date="2005-08-20 19:11:00" coords="037d 47.00 N / 076d 19.00 W" comment="Boadicea anchored in Mill Creek, Ingram Bay, VA"/>
<marker lat="38.3393333333333" lng="-76.4315" src="WINLINK" date="2005-08-21 20:14:00" coords="038d 20.00 N / 076d 25.00 W" comment="Boadicea anchored in Mill Creek, Solomons, MD"/>
<marker lat="38.7466666666667" lng="-76.269" src="WINLINK" date="2005-08-25 19:17:00" coords="038d 44.00 N / 076d 16.00 W" comment="Boadicea anchored in Baby Owl Cove, Leadenham Creek, Broad Creek, MD"/>
<marker lat="38.9036666666667" lng="-76.1573333333333" src="WINLINK" date="2005-08-26 21:25:00" coords="038d 54.00 N / 076d 09.00 W" comment="Boadicea anchored in DeCoursey Cove, Wye River,  MD"/>
<marker lat="38.9665" lng="-76.478" src="WINLINK" date="2005-08-28 19:12:00" coords="038d 57.00 N / 076d 28.00 W" comment="Boadicea tied up Annapolis, MD"/>
<marker lat="38.9763333333333" lng="-76.4826666666667" src="WINLINK" date="2005-09-01 15:05:00" coords="038d 58.00 N / 076d 28.00 W" comment="Boadicea on mooring ball off Naval Academy, MD"/>
<marker lat="39.2946666666667" lng="-76.174" src="WINLINK" date="2005-09-03 20:32:00" coords="039d 17.00 N / 076d 10.00 W" comment="Boadicea anchored off entrance to Tims Creek, Worden,  MD"/>
<marker lat="39.3731666666667" lng="-75.9745" src="WINLINK" date="2005-09-04 21:10:00" coords="039d 22.00 N / 075d 58.00 W" comment="Boadicea anchored Sassafras River, MD"/>
<marker lat="39.3311666666667" lng="-76.1421666666667" src="WINLINK" date="2005-09-05 16:31:00" coords="039d 19.00 N / 076d 08.00 W" comment="Boadicea anchored Still Pond, Chesapeake Bay, MD"/>
<marker lat="39.2823333333333" lng="-76.6088333333333" src="WINLINK" date="2005-09-06 19:31:00" coords="039d 16.00 N / 076d 36.00 W" comment="Boadicea tied up Baltimore Inner Harbor, MD"/>
<marker lat="39.1325" lng="-76.4495" src="WINLINK" date="2005-09-09 19:39:00" coords="039d 07.00 N / 076d 26.00 W" comment="Boadicea anchored Bodkin Creek, Patapsco River, MD"/>
<marker lat="39.3303333333333" lng="-76.1423333333333" src="WINLINK" date="2005-09-11 18:39:00" coords="039d 19.00 N / 076d 08.00 W" comment="Boadicea anchored Still Pond, Chesapeake Bay,  MD"/>
<marker lat="39.2765" lng="-76.6031666666667" src="WINLINK" date="2005-09-12 18:49:00" coords="039d 16.00 N / 076d 36.00 W" comment="Boadicea in a marina in Baltimore, MD, waiting for Hurricane Ophelia to pass."/>
<marker lat="39.4768333333333" lng="-75.9345" src="WINLINK" date="2005-09-17 19:40:00" coords="039d 28.00 N / 075d 56.00 W" comment="Boadicea anchored Veasey Cove, Bohemia River,  MD"/>
<marker lat="38.9501666666667" lng="-74.8856666666667" src="WINLINK" date="2005-09-18 22:49:00" coords="038d 57.00 N / 074d 53.00 W" comment="Boadicea anchored Cape May, NJ"/>
<marker lat="40.4156666666667" lng="-74.021" src="WINLINK" date="2005-09-20 12:44:00" coords="040d 24.00 N / 074d 01.00 W" comment="Boadicea anchored Atlantic Highlands, NJ."/>
<marker lat="40.7893333333333" lng="-73.9835" src="WINLINK" date="2005-09-21 18:23:00" coords="040d 47.00 N / 073d 59.00 W" comment="Boadicea on a mooring ball, 79th Street Boat Basin Marina, Manhattan, New York"/>
<marker lat="40.8958333333333" lng="-73.5313333333333" src="WINLINK" date="2005-10-03 18:43:00" coords="040d 53.00 N / 073d 31.00 W" comment="Boadicea anchored in Oyster Bay, Long Island, NY"/>
<marker lat="40.9658333333333" lng="-73.0971666666667" src="WINLINK" date="2005-10-04 19:19:00" coords="040d 57.00 N / 073d 05.00 W" comment="Boadicea anchored in Port Jefferson, south of Old Field Beach, Long Island"/>
<marker lat="41.0861666666667" lng="-72.351" src="WINLINK" date="2005-10-05 20:44:00" coords="041d 05.00 N / 072d 21.00 W" comment="Boadicea on mooring ball, Shelter Island Yacht Club, Long Island NY"/>
<marker lat="41.4031666666667" lng="-71.5055" src="WINLINK" date="2005-10-10 20:51:00" coords="041d 24.00 N / 071d 30.00 W" comment="Boadicea anchored Point Judith Pond, RI"/>
<marker lat="41.485" lng="-71.3193333333333" src="WINLINK" date="2005-10-11 18:54:00" coords="041d 29.00 N / 071d 19.00 W" comment="Boadicea on a mooring ball, Newport, RI"/>
</markers>