<markers>
<marker lat="34.8166666666667" lng="-46.4" src="" date="2003-06-13 13:00:00" coords="034d 49.00 N / 046d 24.00 W" comment=""/>
<marker lat="34.9333333333333" lng="-39.7166666666667" src="" date="2003-06-16 13:00:00" coords="034d 56.00 N / 039d 43.00 W" comment=""/>
<marker lat="53.6166666666667" lng="6.13333333333333" src="" date="2004-09-02 16:43:00" coords="053d 37.00 N / 006d 08.00 E" comment=""/>
<marker lat="52.6" lng="3.76666666666667" src="" date="2004-09-03 14:53:00" coords="052d 36.00 N / 003d 46.00 E" comment=""/>
<marker lat="51.7833333333333" lng="2.25" src="" date="2004-09-04 05:08:00" coords="051d 47.00 N / 002d 15.00 E" comment=""/>
<marker lat="51.3333333333333" lng="1.41666666666667" src="" date="2004-09-13 06:06:00" coords="051d 20.00 N / 001d 25.00 E" comment=""/>
<marker lat="51.4166666666667" lng="0.7" src="" date="2004-09-27 04:38:00" coords="051d 25.00 N / 000d 42.00 E" comment=""/>
<marker lat="51.5" lng="-0.0666666666666667" src="" date="2005-01-07 15:10:00" coords="051d 30.00 N / 000d 04.00 W" comment=""/>
<marker lat="51.5" lng="-0.0666666666666667" src="" date="2005-02-24 17:46:00" coords="051d 30.00 N / 000d 04.00 W" comment=""/>
<marker lat="51.5" lng="-0.0666666666666667" src="" date="2005-04-07 13:47:00" coords="051d 30.00 N / 000d 04.00 W" comment=""/>
<marker lat="51.4166666666667" lng="0.7" src="" date="2005-04-15 14:10:00" coords="051d 25.00 N / 000d 42.00 E" comment=""/>
<marker lat="51.3333333333333" lng="1.41666666666667" src="" date="2005-04-16 11:57:00" coords="051d 20.00 N / 001d 25.00 E" comment=""/>
<marker lat="50.15" lng="-3.9" src="" date="2005-05-10 20:34:00" coords="050d 09.00 N / 003d 54.00 W" comment=""/>
<marker lat="43.3676666666667" lng="-8.39533333333333" src="WINLINK" date="2005-07-05 03:41:00" coords="043d 22.00 N / 008d 23.00 W" comment="Still in - and enjoying thoroughly, La Coruna, NW corner of Spain"/>
<marker lat="43.134" lng="-9.17516666666667" src="WINLINK" date="2005-07-11 12:58:00" coords="043d 08.00 N / 009d 10.00 W" comment="Mostly around the corner; Cape Finisterre is next; now in Ria Camarinas"/>
<marker lat="42.7581666666667" lng="-9.06383333333333" src="WINLINK" date="2005-07-12 12:47:00" coords="042d 45.00 N / 009d 03.00 W" comment="Soft winds invited us around Cabo Finisterre; anchored Ensenada de San Francisco"/>
<marker lat="42.7796666666667" lng="-9.05883333333333" src="WINLINK" date="2005-07-15 10:29:00" coords="042d 46.00 N / 009d 03.00 W" comment="Moved to Muros for the weekend sea festival; sunny and warm when not foggy"/>
<marker lat="42.7655" lng="-8.94433333333333" src="WINLINK" date="2005-07-17 09:08:00" coords="042d 45.00 N / 008d 56.00 W" comment="Back to Portosin for ''work day'' of laundry, boat scrub and such"/>
<marker lat="42.5651666666667" lng="-8.984" src="WINLINK" date="2005-07-18 12:38:00" coords="042d 33.00 N / 008d 59.00 W" comment="Moved to Ria de Arousa; lovely anchorage off sandy playa, beautiful weather"/>
<marker lat="42.6028333333333" lng="-8.7745" src="WINLINK" date="2005-07-20 13:41:00" coords="042d 36.00 N / 008d 46.00 W" comment="Anchored off VillaGarcia, where we''ll board Adrian and Julia EARLY Tues."/>
<marker lat="42.2583333333333" lng="-8.845" src="WINLINK" date="2005-07-30 12:57:00" coords="042d 15.00 N / 008d 50.00 W" comment="Anchored in Ria de Vigo after visiting trashy Isla de Cies and its plastic baggies"/>
<marker lat="42.2421666666667" lng="-8.72433333333333" src="WINLINK" date="2005-08-01 08:35:00" coords="042d 14.00 N / 008d 43.00 W" comment="Berthed Club Nautico Vigo with a slime line holding us off the pontoon"/>
<marker lat="42.1201666666667" lng="-8.84266666666667" src="WINLINK" date="2005-08-03 20:10:00" coords="042d 07.00 N / 008d 50.00 W" comment="Shifted to Bayona at mouth of Vigo Ria; many cruisers, all going somewhere"/>
<marker lat="41.6935" lng="-8.8225" src="WINLINK" date="2005-08-11 12:05:00" coords="041d 41.00 N / 008d 49.00 W" comment="Departed Spain for Viana do Costello, Portugal; now to find the officials!"/>
<marker lat="40.1471666666667" lng="-8.8595" src="WINLINK" date="2005-08-13 14:51:00" coords="040d 08.00 N / 008d 51.00 W" comment="Berthed in Figueira da Foz; yet more officials and paperwork but it's nice"/>
<marker lat="39.3525" lng="-9.377" src="WINLINK" date="2005-08-15 17:34:00" coords="039d 21.00 N / 009d 22.00 W" comment="Further south to Piniche; minimal berthing and no anchoring...back to rafting!"/>
<marker lat="38.6968333333333" lng="-9.41316666666667" src="WINLINK" date="2005-08-16 15:49:00" coords="038d 41.00 N / 009d 24.00 W" comment="Another murky, hazy motorsail, arriving Lisbon's outskirts - Cascais anchorage"/>
<marker lat="38.7011666666667" lng="-9.16816666666667" src="WINLINK" date="2005-08-21 12:00:00" coords="038d 42.00 N / 009d 10.00 W" comment="Moved up the Tejo R. to Lisbon; will haul on Monday, Oct. 5th"/>
<marker lat="38.7011666666667" lng="-9.16816666666667" src="WINLINK" date="2005-08-29 14:18:00" coords="038d 42.00 N / 009d 10.00 W" comment="Stripping WHOOSH in prep for storage ashore, but also enjoying seeing Lisbon"/>
<marker lat="38.7011666666667" lng="-9.16816666666667" src="WINLINK" date="2005-09-02 14:56:00" coords="038d 42.00 N / 009d 10.00 W" comment="Hot days, cool evenings, lots to see and lots to do on the boat; Lisbon is great"/>
<marker lat="38.6346666666667" lng="-9.11333333333333" src="WINLINK" date="2005-09-05 16:27:00" coords="038d 38.00 N / 009d 06.00 W" comment="Moved to Tagus Yacht Center, the shipyard where we'll leave WHOOSH; haul Wed"/>
<marker lat="38.6345" lng="-9.11333333333333" src="WINLINK" date="2005-09-11 07:24:00" coords="038d 38.00 N / 009d 06.00 W" comment="WHOOSH in steel cradle ashore, stripped and looking forlorn; fly back Wed."/>
</markers>