<markers>
<marker lat="52.8333333333333" lng="4.75" src="" date="2005-03-22 10:14:00" coords="052d 50.00 N / 004d 45.00 E" comment=""/>
<marker lat="52.8333333333333" lng="4.75" src="" date="2005-03-26 09:20:00" coords="052d 50.00 N / 004d 45.00 E" comment=""/>
<marker lat="52.8333333333333" lng="4.75" src="" date="2005-03-31 09:51:00" coords="052d 50.00 N / 004d 45.00 E" comment=""/>
<marker lat="52.8333333333333" lng="4.75" src="" date="2005-03-31 14:07:00" coords="052d 50.00 N / 004d 45.00 E" comment=""/>
<marker lat="53.1166666666667" lng="5.91666666666667" src="" date="2005-05-01 18:47:00" coords="053d 07.00 N / 005d 55.00 E" comment=""/>
<marker lat="52.8333333333333" lng="4.76666666666667" src="" date="2005-05-04 06:48:00" coords="052d 50.00 N / 004d 46.00 E" comment=""/>
<marker lat="52.8333333333333" lng="4.76666666666667" src="" date="2005-05-07 07:14:00" coords="052d 50.00 N / 004d 46.00 E" comment=""/>
<marker lat="53.0485" lng="13.2985" src="WINLINK" date="2005-06-30 15:32:00" coords="053d 02.00 N / 013d 17.00 E" comment="Burgwall"/>
<marker lat="52.6835" lng="13.2445" src="WINLINK" date="2005-07-01 14:46:00" coords="052d 41.00 N / 013d 14.00 E" comment="Berlin area"/>
<marker lat="52.5011666666667" lng="13.1868333333333" src="WINLINK" date="2005-07-02 19:43:00" coords="052d 30.00 N / 013d 11.00 E" comment="Spandauersee Spandau Berlin Area"/>
<marker lat="52.5011666666667" lng="13.1868333333333" src="WINLINK" date="2005-07-05 08:45:00" coords="052d 30.00 N / 013d 11.00 E" comment="Spandauersee Spandau Berlin Area"/>
<marker lat="52.4166666666667" lng="12.623" src="WINLINK" date="2005-07-07 16:46:00" coords="052d 25.00 N / 012d 37.00 E" comment="Brandenburg"/>
<marker lat="52.2826666666667" lng="11.8485" src="WINLINK" date="2005-07-08 16:58:00" coords="052d 16.00 N / 011d 50.00 E" comment=""/>
<marker lat="52.279" lng="11.4033333333333" src="WINLINK" date="2005-07-09 12:50:00" coords="052d 16.00 N / 011d 24.00 E" comment="Haldensleben Mittellandkanal"/>
<marker lat="52.4313333333333" lng="10.8061666666667" src="WINLINK" date="2005-07-10 19:49:00" coords="052d 25.00 N / 010d 48.00 E" comment="Wolfsburg Mittellandkanal"/>
<marker lat="52.384" lng="9.871" src="WINLINK" date="2005-07-12 20:10:00" coords="052d 23.00 N / 009d 52.00 E" comment="Hannover Mittellandkanal"/>
<marker lat="52.3901666666667" lng="9.35283333333333" src="WINLINK" date="2005-07-13 20:28:00" coords="052d 23.00 N / 009d 21.00 E" comment="Idensen Mittellandkanal"/>
<marker lat="52.3398333333333" lng="7.95333333333333" src="WINLINK" date="2005-07-15 20:45:00" coords="052d 20.00 N / 007d 57.00 E" comment="Osnabrück Mittellandkanal"/>
<marker lat="52.3398333333333" lng="7.95333333333333" src="WINLINK" date="2005-07-17 19:16:00" coords="052d 20.00 N / 007d 57.00 E" comment="Osnabrück Mittellandkanal"/>
<marker lat="52.0473333333333" lng="7.68766666666667" src="WINLINK" date="2005-07-18 20:35:00" coords="052d 02.00 N / 007d 41.00 E" comment="Osnabrück Mittellandkanal"/>
<marker lat="51.845" lng="7.46883333333333" src="WINLINK" date="2005-07-19 15:01:00" coords="051d 50.00 N / 007d 28.00 E" comment="DEK"/>
<marker lat="51.6618333333333" lng="6.58816666666667" src="WINLINK" date="2005-07-20 20:59:00" coords="051d 39.00 N / 006d 35.00 E" comment="Wesel Rhine"/>
<marker lat="51.6616666666667" lng="6.58816666666667" src="WINLINK" date="2005-07-22 17:36:00" coords="051d 39.00 N / 006d 35.00 E" comment="Wesel Rhine"/>
<marker lat="51.9891666666667" lng="6.04883333333333" src="WINLINK" date="2005-07-23 18:52:00" coords="051d 59.00 N / 006d 02.00 E" comment="De Steeg Ijssel"/>
<marker lat="51.9891666666667" lng="6.049" src="WINLINK" date="2005-07-25 06:02:00" coords="051d 59.00 N / 006d 02.00 E" comment="De Steeg Ijssel"/>
<marker lat="52.3463333333333" lng="6.1045" src="WINLINK" date="2005-07-26 09:49:00" coords="052d 20.00 N / 006d 06.00 E" comment="IJssel"/>
<marker lat="52.4786666666667" lng="6.06866666666667" src="WINLINK" date="2005-07-26 13:55:00" coords="052d 28.00 N / 006d 04.00 E" comment="Hattum IJssel"/>
<marker lat="53.1341666666667" lng="5.94616666666667" src="WINLINK" date="2005-07-27 19:36:00" coords="053d 08.00 N / 005d 56.00 E" comment="Eernewoude"/>
<marker lat="52.8405" lng="4.76466666666667" src="WINLINK" date="2005-07-30 12:22:00" coords="052d 50.00 N / 004d 45.00 E" comment="Home"/>
<marker lat="52.8358333333333" lng="4.75533333333333" src="WINLINK" date="2005-08-25 10:48:00" coords="052d 50.00 N / 004d 45.00 E" comment="Home"/>
</markers>