<markers>
<marker lat="-37.4" lng="177.066666666667" src="" date="2005-04-07 07:21:00" coords="037d 24.00 S / 177d 04.00 E" comment=""/>
<marker lat="-37.75" lng="-179.833333333333" src="" date="2005-04-08 06:51:00" coords="037d 45.00 S / 179d 50.00 W" comment=""/>
<marker lat="-39.4" lng="178.15" src="" date="2005-04-09 07:59:00" coords="039d 24.00 S / 178d 09.00 E" comment=""/>
<marker lat="-40.2833333333333" lng="-175.333333333333" src="" date="2005-04-10 09:07:00" coords="040d 17.00 S / 175d 20.00 W" comment=""/>
<marker lat="-41.5" lng="-172.816666666667" src="" date="2005-04-11 07:22:00" coords="041d 30.00 S / 172d 49.00 W" comment=""/>
<marker lat="-41.25" lng="-172.016666666667" src="" date="2005-04-12 06:27:00" coords="041d 15.00 S / 172d 01.00 W" comment=""/>
<marker lat="-40.85" lng="-170.933333333333" src="" date="2005-04-13 05:45:00" coords="040d 51.00 S / 170d 56.00 W" comment=""/>
<marker lat="-39.7333333333333" lng="-166.983333333333" src="" date="2005-04-14 11:52:00" coords="039d 44.00 S / 166d 59.00 W" comment=""/>
<marker lat="-39.2666666666667" lng="-163.966666666667" src="" date="2005-04-15 07:48:00" coords="039d 16.00 S / 163d 58.00 W" comment=""/>
<marker lat="-38.3333333333333" lng="-160.916666666667" src="" date="2005-04-16 05:15:00" coords="038d 20.00 S / 160d 55.00 W" comment=""/>
<marker lat="-36.7" lng="-157.9" src="" date="2005-04-17 05:15:00" coords="036d 42.00 S / 157d 54.00 W" comment=""/>
<marker lat="-34.9833333333333" lng="-155.833333333333" src="" date="2005-04-18 04:34:00" coords="034d 59.00 S / 155d 50.00 W" comment=""/>
<marker lat="-33.7666666666667" lng="-153.666666666667" src="" date="2005-04-19 04:19:00" coords="033d 46.00 S / 153d 40.00 W" comment=""/>
<marker lat="-32" lng="-151.3" src="" date="2005-04-20 07:32:00" coords="032d 00.00 S / 151d 18.00 W" comment=""/>
<marker lat="-29.8166666666667" lng="-149.3" src="" date="2005-04-21 06:26:00" coords="029d 49.00 S / 149d 18.00 W" comment=""/>
<marker lat="-27.25" lng="-147.566666666667" src="" date="2005-04-22 06:28:00" coords="027d 15.00 S / 147d 34.00 W" comment=""/>
<marker lat="-24.2166666666667" lng="-147.433333333333" src="" date="2005-04-23 10:09:00" coords="024d 13.00 S / 147d 26.00 W" comment=""/>
<marker lat="-20.55" lng="-146.9" src="" date="2005-04-30 08:51:00" coords="020d 33.00 S / 146d 54.00 W" comment=""/>
<marker lat="-18.2333333333333" lng="-146.316666666667" src="" date="2005-05-01 08:15:00" coords="018d 14.00 S / 146d 19.00 W" comment=""/>
<marker lat="-16.5333333333333" lng="-145.95" src="" date="2005-05-02 08:29:00" coords="016d 32.00 S / 145d 57.00 W" comment=""/>
<marker lat="-16.05" lng="-145.616666666667" src="" date="2005-05-03 06:59:00" coords="016d 03.00 S / 145d 37.00 W" comment=""/>
<marker lat="-16.4" lng="-146.683333333333" src="" date="2005-05-06 05:30:00" coords="016d 24.00 S / 146d 41.00 W" comment=""/>
<marker lat="-17.5666666666667" lng="-149.616666666667" src="" date="2005-05-09 05:33:00" coords="017d 34.00 S / 149d 37.00 W" comment=""/>
<marker lat="-15.6333333333333" lng="-149.2" src="" date="2005-05-15 20:08:00" coords="015d 38.00 S / 149d 12.00 W" comment=""/>
<marker lat="-15.1" lng="-148.966666666667" src="" date="2005-05-16 02:14:00" coords="015d 06.00 S / 148d 58.00 W" comment=""/>
<marker lat="-13.9" lng="-147.216666666667" src="" date="2005-05-17 03:00:00" coords="013d 54.00 S / 147d 13.00 W" comment=""/>
<marker lat="-13.2666666666667" lng="-145.116666666667" src="" date="2005-05-18 02:27:00" coords="013d 16.00 S / 145d 07.00 W" comment=""/>
<marker lat="-13.2" lng="-143.333333333333" src="" date="2005-05-19 01:56:00" coords="013d 12.00 S / 143d 20.00 W" comment=""/>
<marker lat="-13.25" lng="-141.5" src="" date="2005-05-20 01:58:00" coords="013d 15.00 S / 141d 30.00 W" comment=""/>
<marker lat="-12.8" lng="-140.2" src="" date="2005-05-21 02:05:00" coords="012d 48.00 S / 140d 12.00 W" comment=""/>
<marker lat="-10.8333333333333" lng="-140.866666666667" src="" date="2005-05-22 01:57:00" coords="010d 50.00 S / 140d 52.00 W" comment=""/>
<marker lat="-8.46666666666667" lng="-141" src="" date="2005-05-23 02:00:00" coords="008d 28.00 S / 141d 00.00 W" comment=""/>
<marker lat="-6.06666666666667" lng="-141.25" src="" date="2005-05-24 02:00:00" coords="006d 04.00 S / 141d 15.00 W" comment=""/>
<marker lat="-4.15" lng="-141.35" src="" date="2005-05-25 03:45:00" coords="004d 09.00 S / 141d 21.00 W" comment=""/>
<marker lat="-1.48333333333333" lng="-141.783333333333" src="" date="2005-05-26 02:57:00" coords="001d 29.00 S / 141d 47.00 W" comment=""/>
<marker lat="1.45" lng="-141.633333333333" src="" date="2005-05-27 02:38:00" coords="001d 27.00 N / 141d 38.00 W" comment=""/>
<marker lat="4.21666666666667" lng="-141.5" src="" date="2005-05-28 03:10:00" coords="004d 13.00 N / 141d 30.00 W" comment=""/>
<marker lat="6.83333333333333" lng="-141.766666666667" src="" date="2005-05-29 03:18:00" coords="006d 50.00 N / 141d 46.00 W" comment=""/>
<marker lat="9.21666666666667" lng="-143.45" src="" date="2005-05-30 03:04:00" coords="009d 13.00 N / 143d 27.00 W" comment=""/>
<marker lat="11.55" lng="-145.833333333333" src="" date="2005-05-31 03:23:00" coords="011d 33.00 N / 145d 50.00 W" comment=""/>
<marker lat="13.7333333333333" lng="-148.266666666667" src="" date="2005-06-01 03:14:00" coords="013d 44.00 N / 148d 16.00 W" comment=""/>
<marker lat="15.9833333333333" lng="-150.816666666667" src="" date="2005-06-02 03:14:00" coords="015d 59.00 N / 150d 49.00 W" comment=""/>
<marker lat="19.7166666666667" lng="-155.05" src="" date="2005-06-06 03:45:00" coords="019d 43.00 N / 155d 03.00 W" comment=""/>
<marker lat="21.3" lng="-157.15" src="" date="2005-06-16 03:24:00" coords="021d 18.00 N / 157d 09.00 W" comment=""/>
<marker lat="21.6" lng="-158.316666666667" src="" date="2005-06-22 03:39:00" coords="021d 36.00 N / 158d 19.00 W" comment=""/>
<marker lat="24.2166666666667" lng="-158.533333333333" src="" date="2005-06-23 02:00:00" coords="024d 13.00 N / 158d 32.00 W" comment=""/>
<marker lat="27.25" lng="-159" src="" date="2005-06-24 02:13:00" coords="027d 15.00 N / 159d 00.00 W" comment=""/>
<marker lat="30.1333333333333" lng="-159.166666666667" src="" date="2005-06-25 02:45:00" coords="030d 08.00 N / 159d 10.00 W" comment=""/>
<marker lat="32.3" lng="-159" src="" date="2005-06-26 02:45:00" coords="032d 18.00 N / 159d 00.00 W" comment=""/>
<marker lat="35.0166666666667" lng="-158.233333333333" src="" date="2005-06-27 03:14:00" coords="035d 01.00 N / 158d 14.00 W" comment=""/>
<marker lat="37.3833333333333" lng="-157.216666666667" src="" date="2005-06-28 06:54:00" coords="037d 23.00 N / 157d 13.00 W" comment=""/>
<marker lat="38.8" lng="-157.033333333333" src="" date="2005-06-29 02:37:00" coords="038d 48.00 N / 157d 02.00 W" comment=""/>
<marker lat="40.75" lng="-156.066666666667" src="" date="2005-06-30 02:04:00" coords="040d 45.00 N / 156d 04.00 W" comment=""/>
<marker lat="42.8333333333333" lng="-154.633333333333" src="" date="2005-07-01 02:15:00" coords="042d 50.00 N / 154d 38.00 W" comment=""/>
<marker lat="44.7166666666667" lng="-152.683333333333" src="" date="2005-07-02 03:02:00" coords="044d 43.00 N / 152d 41.00 W" comment=""/>
<marker lat="46.7333333333333" lng="-150.333333333333" src="" date="2005-07-03 02:54:00" coords="046d 44.00 N / 150d 20.00 W" comment=""/>
<marker lat="49.2333333333333" lng="-147.233333333333" src="" date="2005-07-04 08:59:00" coords="049d 14.00 N / 147d 14.00 W" comment=""/>
<marker lat="50.6166666666667" lng="-145.533333333333" src="" date="2005-07-05 02:48:00" coords="050d 37.00 N / 145d 32.00 W" comment=""/>
<marker lat="53.0666666666667" lng="-141.766666666667" src="" date="2005-07-06 07:42:00" coords="053d 04.00 N / 141d 46.00 W" comment=""/>
<marker lat="54.4833333333333" lng="-138.8" src="" date="2005-07-07 06:35:00" coords="054d 29.00 N / 138d 48.00 W" comment=""/>
<marker lat="56.15" lng="-136.533333333333" src="" date="2005-07-08 02:36:00" coords="056d 09.00 N / 136d 32.00 W" comment=""/>
</markers>