<markers>
<marker lat="44.4196666666667" lng="-73.4263333333333" src="WINLINK" date="2005-07-26 02:11:00" coords="044d 25.00 N / 073d 25.00 W" comment="test"/>
<marker lat="44.3766666666667" lng="-73.2776666666667" src="WINLINK" date="2005-07-31 12:42:00" coords="044d 22.00 N / 073d 16.00 W" comment=""/>
<marker lat="44.3986666666667" lng="-73.3916666666667" src="WINLINK" date="2005-08-29 00:48:00" coords="044d 23.00 N / 073d 23.00 W" comment="12 jours avant le grand depart, Willsboro bay. Tres belle soirée..."/>
<marker lat="42.07" lng="-73.9416666666667" src="WINLINK" date="2005-09-22 00:28:00" coords="042d 04.00 N / 073d 56.00 W" comment="Journée très chaude pour ré-armer le bateau...."/>
<marker lat="40.7911666666667" lng="-73.9835" src="WINLINK" date="2005-09-25 00:22:00" coords="040d 47.00 N / 073d 59.00 W" comment="Journée très chaude pour ré-armer le bateau...."/>
<marker lat="39.3865" lng="-74.4096666666667" src="WINLINK" date="2005-09-28 21:22:00" coords="039d 23.00 N / 074d 24.00 W" comment="on navigue depuis 2 jours sur l'Atlantique.Notre arret ce soir Atlantic City"/>
<marker lat="38.9501666666667" lng="-74.8875" src="WINLINK" date="2005-09-30 23:14:00" coords="038d 57.00 N / 074d 53.00 W" comment="Une belle journée ensoleillée à voile pour se rendre à Cape May"/>
<marker lat="39.3531666666667" lng="-75.361" src="WINLINK" date="2005-10-01 22:09:00" coords="039d 21.00 N / 075d 21.00 W" comment="Un soleil radieux pour la traversée de la Bay the Delaware"/>
<marker lat="39.5256666666667" lng="-75.8088333333333" src="WINLINK" date="2005-10-02 19:47:00" coords="039d 31.00 N / 075d 48.00 W" comment="Ensoleillée 90 degré à Chesepeake City"/>
<marker lat="39.3715" lng="-75.9758333333333" src="WINLINK" date="2005-10-03 20:30:00" coords="039d 22.00 N / 075d 58.00 W" comment="Belle soirée dans une petite baie tranquille.Ensoleillée ajourd'hui 88 degré"/>
<marker lat="38.9633333333333" lng="-76.4813333333333" src="WINLINK" date="2005-10-04 20:27:00" coords="038d 57.00 N / 076d 28.00 W" comment="Agglutinnés comme des sardines à Annapolis pour une semaine"/>
<marker lat="38.7888333333333" lng="-76.2193333333333" src="WINLINK" date="2005-10-11 14:11:00" coords="038d 47.00 N / 076d 13.00 W" comment="Accueuillis par des cygnes dans la petite ville de St-Michael... un bel oasis"/>
<marker lat="38.3318333333333" lng="-76.4595" src="WINLINK" date="2005-10-15 21:43:00" coords="038d 19.00 N / 076d 27.00 W" comment="45 milles à voile pour se rendre à Solomon...magnifique journée ensoleillée"/>
<marker lat="37.7925" lng="-76.3218333333333" src="WINLINK" date="2005-10-20 00:39:00" coords="037d 47.00 N / 076d 19.00 W" comment="Magnifique couher de soleil riviere WICOMICO"/>
<marker lat="37.549" lng="-76.3318333333333" src="WINLINK" date="2005-10-22 20:27:00" coords="037d 32.00 N / 076d 19.00 W" comment="Soirée romantique à Deltaville"/>
</markers>