<markers>
<marker lat="29.0666666666667" lng="-80.8666666666667" src="" date="2003-11-26 20:29:00" coords="029d 04.00 N / 080d 52.00 W" comment=""/>
<marker lat="26.8333333333333" lng="-80.8666666666667" src="" date="2003-11-27 23:42:00" coords="026d 50.00 N / 080d 52.00 W" comment=""/>
<marker lat="26.0833333333333" lng="-80.1166666666667" src="" date="2003-11-28 22:44:00" coords="026d 05.00 N / 080d 07.00 W" comment=""/>
<marker lat="25.7666666666667" lng="-80.1333333333333" src="" date="2003-11-30 00:24:00" coords="025d 46.00 N / 080d 08.00 W" comment=""/>
<marker lat="24.5333333333333" lng="-81.8166666666667" src="" date="2003-12-01 10:28:00" coords="024d 32.00 N / 081d 49.00 W" comment=""/>
<marker lat="24.5666666666667" lng="-81.8" src="" date="2003-12-05 18:25:00" coords="024d 34.00 N / 081d 48.00 W" comment=""/>
<marker lat="24.4" lng="-82.3333333333333" src="" date="2003-12-07 19:10:00" coords="024d 24.00 N / 082d 20.00 W" comment=""/>
<marker lat="24.1666666666667" lng="-82.6833333333333" src="" date="2003-12-07 23:19:00" coords="024d 10.00 N / 082d 41.00 W" comment=""/>
<marker lat="23.2" lng="-83.4666666666667" src="" date="2003-12-08 11:39:00" coords="023d 12.00 N / 083d 28.00 W" comment=""/>
<marker lat="22.45" lng="-84.6333333333333" src="" date="2003-12-09 00:07:00" coords="022d 27.00 N / 084d 38.00 W" comment=""/>
<marker lat="21.0833333333333" lng="-86.75" src="" date="2003-12-15 15:42:00" coords="021d 05.00 N / 086d 45.00 W" comment=""/>
<marker lat="19.7" lng="-87.35" src="" date="2003-12-16 10:36:00" coords="019d 42.00 N / 087d 21.00 W" comment=""/>
<marker lat="18.9333333333333" lng="-87.6" src="" date="2003-12-16 20:32:00" coords="018d 56.00 N / 087d 36.00 W" comment=""/>
<marker lat="17.3666666666667" lng="-88.0833333333333" src="" date="2003-12-17 14:57:00" coords="017d 22.00 N / 088d 05.00 W" comment=""/>
<marker lat="16.4" lng="-88.3833333333333" src="" date="2003-12-19 00:59:00" coords="016d 24.00 N / 088d 23.00 W" comment=""/>
<marker lat="15.75" lng="-88.8333333333333" src="" date="2005-01-06 23:21:00" coords="015d 45.00 N / 088d 50.00 W" comment=""/>
<marker lat="15.8" lng="-88.75" src="" date="2005-01-08 20:43:00" coords="015d 48.00 N / 088d 45.00 W" comment=""/>
<marker lat="24.6166666666667" lng="-82.8666666666667" src="" date="2005-03-28 00:32:00" coords="024d 37.00 N / 082d 52.00 W" comment=""/>
<marker lat="24.6166666666667" lng="-82.8666666666667" src="" date="2005-03-29 14:37:00" coords="024d 37.00 N / 082d 52.00 W" comment=""/>
<marker lat="23.5666666666667" lng="-83.85" src="" date="2005-03-30 14:58:00" coords="023d 34.00 N / 083d 51.00 W" comment=""/>
<marker lat="21.8166666666667" lng="-85.25" src="" date="2005-03-31 18:09:00" coords="021d 49.00 N / 085d 15.00 W" comment=""/>
<marker lat="21.5333333333333" lng="-85.7166666666667" src="" date="2005-04-01 00:15:00" coords="021d 32.00 N / 085d 43.00 W" comment=""/>
<marker lat="21.25" lng="-86.75" src="" date="2005-04-02 20:12:00" coords="021d 15.00 N / 086d 45.00 W" comment=""/>
<marker lat="20.5" lng="-86.95" src="" date="2005-04-12 16:48:00" coords="020d 30.00 N / 086d 57.00 W" comment=""/>
<marker lat="19.7" lng="-87.5" src="" date="2005-04-14 22:56:00" coords="019d 42.00 N / 087d 30.00 W" comment=""/>
<marker lat="19.55" lng="-87.4" src="" date="2005-04-15 20:25:00" coords="019d 33.00 N / 087d 24.00 W" comment=""/>
<marker lat="19.2" lng="-87.4333333333333" src="" date="2005-04-16 19:26:00" coords="019d 12.00 N / 087d 26.00 W" comment=""/>
<marker lat="18.8" lng="-87.6333333333333" src="" date="2005-04-17 01:23:00" coords="018d 48.00 N / 087d 38.00 W" comment=""/>
<marker lat="17.2333333333333" lng="-88.0833333333333" src="" date="2005-04-28 23:03:00" coords="017d 14.00 N / 088d 05.00 W" comment=""/>
<marker lat="16.6833333333333" lng="-88.1833333333333" src="" date="2005-04-29 23:55:00" coords="016d 41.00 N / 088d 11.00 W" comment=""/>
<marker lat="16.2333333333333" lng="-88.4833333333333" src="" date="2005-05-01 20:31:00" coords="016d 14.00 N / 088d 29.00 W" comment=""/>
<marker lat="15.8333333333333" lng="-88.7166666666667" src="" date="2005-05-02 13:18:00" coords="015d 50.00 N / 088d 43.00 W" comment=""/>
<marker lat="15.83" lng="-88.723" src="WINLINK" date="2005-09-06 17:48:00" coords="015d 49.00 N / 088d 43.00 W" comment="Cayo Quemado, Guatemala."/>
<marker lat="15.65" lng="-89" src="WINLINK" date="2005-09-11 15:41:00" coords="015d 39.00 N / 089d 00.00 W" comment="Tortugal marina, Guatemala"/>
<marker lat="15.65" lng="-89" src="WINLINK" date="2005-09-18 18:15:00" coords="015d 39.00 N / 089d 00.00 W" comment="Tortugal marina, Guatemala"/>
<marker lat="15.65" lng="-89" src="WINLINK" date="2005-10-02 14:45:00" coords="015d 39.00 N / 089d 00.00 W" comment="Tortugal marina, Guatemala"/>
<marker lat="15.754" lng="-88.8386666666667" src="WINLINK" date="2005-10-06 21:03:00" coords="015d 45.00 N / 088d 50.00 W" comment="Tortugal marina, Guatemala"/>
<marker lat="15.754" lng="-88.8386666666667" src="WINLINK" date="2005-10-14 15:12:00" coords="015d 45.00 N / 088d 50.00 W" comment="Cayo Quemado, Guatemala"/>
<marker lat="15.6505" lng="-89.0013333333333" src="WINLINK" date="2005-10-18 23:01:00" coords="015d 39.00 N / 089d 00.00 W" comment="Cayo Quemado, Guatemala"/>
<marker lat="15.6505" lng="-89.0013333333333" src="WINLINK" date="2005-10-18 23:02:00" coords="015d 39.00 N / 089d 00.00 W" comment="Safe at Anchor at Tortugal Marina, Guatemala"/>
<marker lat="15.6505" lng="-89.0013333333333" src="WINLINK" date="2005-10-19 20:50:00" coords="015d 39.00 N / 089d 00.00 W" comment="Safe at Anchor  Tortugal Marina, Guatemala"/>
</markers>