{"positions":[{"lat":10.2078333333,"comment":"Final Provisioning Puerto LaCruz","lon":-64.663,"date":1122772380000},{"lat":10.989,"comment":"Anchored in Isla Tortuga","lon":-65.383,"date":1122943980000},{"lat":11.9463333333,"comment":"Anchored in Isla Tortuga","lon":-67.4338333333,"date":1123118280000},{"lat":11.9651666667,"comment":"Anchored in Isla Aves","lon":-67.4093333333,"date":1123939320000},{"lat":11.9795,"comment":"Anchored in Isla Aves","lon":-67.66,"date":1124975820000},{"lat":11.9913333333,"comment":"Sotavento Isla Aves","lon":-67.6821666667,"date":1125876720000},{"lat":10.9063333333,"comment":"Chichiriviche Venezuela","lon":-68.257,"date":1126033860000},{"lat":12.155,"comment":"Chichiriviche Venezuela","lon":-68.28,"date":1126136640000},{"lat":12.0791666667,"comment":"Chichiriviche Venezuela","lon":-68.8623333333,"date":1126225560000}]}