{"positions":[{"lat":39.0655,"comment":"Sailing soon.....","lon":-76.5013333333,"date":1120126380000},{"lat":39.0655,"comment":"Expect to head north by mid week, Hurrah....","lon":-76.5013333333,"date":1120387860000},{"lat":39.0655,"comment":"Expect to head north tomorrow, Hurrah....","lon":-76.5013333333,"date":1120474800000},{"lat":39.0655,"comment":"Headed north today, Hurrah....","lon":-76.5013333333,"date":1120559100000},{"lat":39.4815,"comment":"Ancored in the Bohemia river....","lon":-75.9365,"date":1120602360000},{"lat":40.4185,"comment":"Ancored at the Alantic Heights Yacht Club....","lon":-74.0306666667,"date":1120747800000},{"lat":40.4185,"comment":"At the Alantic Heights Yacht Club, headed north through NY City today....","lon":-74.0306666667,"date":1120905960000},{"lat":40.9605,"comment":"Ancored at Port Jefferson, NY...","lon":-73.0885,"date":1120947300000},{"lat":41.3281666667,"comment":"Ancored at Stonington, CT...Beautiful view from anchorage...","lon":-71.9126666667,"date":1121035740000},{"lat":41.4846666667,"comment":"Moored in Newport, RI....  Headed in to town...","lon":-71.3203333333,"date":1121096040000},{"lat":41.7075,"comment":"Moored at Marion, MA...","lon":-70.7588333333,"date":1121279340000},{"lat":42.4956666667,"comment":"Moored at Marblehead, MA...   Fantastic sail across Cape Cod Bay....","lon":-70.8488333333,"date":1121376900000},{"lat":43.8473333333,"comment":"Moored booth Bay Maine..  Long foggy day...  Nice to be in...","lon":-69.6278333333,"date":1121730240000},{"lat":44.1201666667,"comment":"Anchored in Carver Cove, Vinalhaven Island Maine...  Beautiful...","lon":-68.8348333333,"date":1121891460000},{"lat":44.0986666667,"comment":"Moored in Rockland, ME...   weather remains wonderful...","lon":-69.0971666667,"date":1122116760000},{"lat":44.4685,"comment":"Hurrah is on her own Maine mooring in Stockton Springs, ME..  Beautiful day...","lon":-68.8605,"date":1122156300000},{"lat":44.4685,"comment":"Moored in Stockton Springs, ME..  Will be here until tomorrow...","lon":-68.8605,"date":1122284160000},{"lat":44.3703333333,"comment":"Anchored in Holbrook Harbor...  Will dinghy over to Castine...","lon":-68.7915,"date":1122397980000},{"lat":44.338,"comment":"Moored in Bucks Harbor Maine...  great place...","lon":-68.7345,"date":1122475920000},{"lat":44.3483333333,"comment":"Great Cove anchorage, quintessential Maine Anchorage.  Loons, seals, porpoises.","lon":-68.4233333333,"date":1122588300000},{"lat":44.405,"comment":"Moored at Blue Hill, ME..  Nice harbor, perfect day..","lon":-68.5645,"date":1122655260000},{"lat":44.405,"comment":"Moored in Frenchboro Long Island, ME...  Perfect day...","lon":-68.5645,"date":1122737640000},{"lat":44.121,"comment":"Moored in Frenchboro Long Island, ME...  Perfect day...","lon":-68.3636666667,"date":1122737700000},{"lat":44.1406666667,"comment":"Moored in Burnt Coat Harbor, ME...  Another perfect day...","lon":-68.448,"date":1122823800000},{"lat":44.1515,"comment":"Anchored at Camp Island, ME..  Fog, wind, rain - now that's more like Maine...","lon":-68.6248333333,"date":1122909960000},{"lat":44.1201666667,"comment":"Anchored in Carter Cove, Vinalhaven, ME..  Beautiful Day...","lon":-68.8348333333,"date":1123095000000},{"lat":44.2798333333,"comment":"Anchored at Islesboro, ME for the SSCA gam...","lon":-68.9333333333,"date":1123239420000},{"lat":44.2798333333,"comment":"Anchored at Islesboro, ME for the SSCA gam...","lon":-68.9333333333,"date":1123320480000},{"lat":44.1053333333,"comment":"Journeys End Marina, Rockland, ME for 4 days...","lon":-69.102,"date":1123453560000},{"lat":44.1065,"comment":"Hurrah is back in the water with new cutlass bearings, Hurrah...  Rockland, ME.","lon":-69.099,"date":1123927440000},{"lat":44.169,"comment":"Anchored in Webb Cove, Dear Island, ME...","lon":-68.6375,"date":1123973640000},{"lat":44.169,"comment":"Anchored in Webb Cove, Deer Island, ME...","lon":-68.6375,"date":1123975620000},{"lat":44.2961666667,"comment":"Moored in Northeast Harbor, ME...","lon":-68.2831666667,"date":1124031180000},{"lat":43.8476666667,"comment":"Moored in Boothbay Harbor...","lon":-69.6276666667,"date":1124227200000},{"lat":43.0726666667,"comment":"Moored in Portsmouth, NH.....  Nice day...","lon":-70.7118333333,"date":1124312400000},{"lat":42.6103333333,"comment":"Anchored in Gloucester Harbor...","lon":-70.6566666667,"date":1124387280000},{"lat":42.4961666667,"comment":"Moored in Marblehead Harbor for a week...","lon":-70.8491666667,"date":1124476920000},{"lat":42.4961666667,"comment":"Moored in Marblehead Harbor for a week...","lon":-70.8491666667,"date":1124794380000},{"lat":41.7078333333,"comment":"Moored in Marion, MA...","lon":-70.7595,"date":1125186840000},{"lat":41.4848333333,"comment":"Moored in Newport,RI, Harbor....  Nice sail today...","lon":-71.3196666667,"date":1125253500000},{"lat":41.329,"comment":"Anchored in Stonington, CT..  Good sail in a heavy rain...","lon":-71.9141666667,"date":1125351720000},{"lat":40.9508333333,"comment":"Moored in port Jef, NY...  Hevy rain but a reefed great sail on the wind...","lon":-73.0698333333,"date":1125434460000},{"lat":40.9121666667,"comment":"Anchored in Northport, NY...  Beautiful day...","lon":-73.3625,"date":1125611400000},{"lat":40.8826666667,"comment":"Anchored in Oyster Bay, NY...  Another beautiful day...","lon":-73.5121666667,"date":1125833520000},{"lat":40.8311666667,"comment":"Moored at Port Washington, NY...  Perfict weather...","lon":-73.7143333333,"date":1126002420000},{"lat":40.7256666667,"comment":"Marina in Jersey City, headed into NY...","lon":-74.0318333333,"date":1126034820000},{"lat":39.3745,"comment":"Anchored in the Sassafras River , Chesapeake Bay.  Long run from NY City.","lon":-76.061,"date":1126393140000},{"lat":39.0648333333,"comment":"Hurrah on her Maryland Mooring...","lon":-76.4981666667,"date":1126606920000}]}