{"positions":[{"lat":44.9333333333,"comment":"","lon":-59.6333333333,"date":1057814220000},{"lat":39.9666666667,"comment":"","lon":-33.9833333333,"date":1058699520000},{"lat":41.93,"comment":"A Ajacio en Corse, au mouillage . Temps superbe","lon":8.7456666667,"date":1120148820000},{"lat":42.3483333333,"comment":"A Girolata en Corse, au mouillage . Temps superbe,","lon":8.6153333333,"date":1120397460000},{"lat":42.4396666667,"comment":"En route vers Toulon, calme plat,  inquitant.","lon":8.2316666667,"date":1120467300000},{"lat":43.1768333333,"comment":"Au mouillage devant une plage   Cavalaire sur mer,. bonne protection du Mistral","lon":6.541,"date":1120573980000}]}